README.md
setup.py
rasp_util/__init__.py
rasp_util/auto_patch.py
rasp_util.egg-info/PKG-INFO
rasp_util.egg-info/SOURCES.txt
rasp_util.egg-info/dependency_links.txt
rasp_util.egg-info/requires.txt
rasp_util.egg-info/top_level.txt
rasp_util/attack_rules/risk_level.py
rasp_util/attack_rules/rules.py
rasp_util/hook_func/hook_func.py
rasp_util/hook_func/operate.py
rasp_util/monkey_patch/command_patch.py
rasp_util/monkey_patch/file_patch.py
rasp_util/monkey_patch/finder.py
rasp_util/monkey_patch/flask_patch.py
rasp_util/monkey_patch/http_server_patch.py
rasp_util/monkey_patch/sql_patch.py
rasp_util/sentry/util.py