Metadata-Version: 1.2
Name: rasp-util
Version: 1.0.7
Summary: RASP project
Home-page: https://github.com/pypa/sampleproject
Author: The Python Packaging Authority
Author-email: pypa-dev@googlegroups.com
License: UNKNOWN
Keywords: sample setuptools development
Platform: UNKNOWN
Requires-Python: >=3.4.0
